utesting/__init__.py
utesting-2.3.0.dist-info/LICENSE
utesting-2.3.0.dist-info/METADATA
utesting-2.3.0.dist-info/WHEEL
utesting-2.3.0.dist-info/top_level.txt
utesting-2.3.0.dist-info/RECORD
