Metadata-Version: 2.1
Name: utesting
Version: 2.3.0
Summary: Module for unit testing
Author: s0urce
Author-email: boyarkin.gleb@gmail.com
Classifier: Programming Language :: Python :: 3
Classifier: License :: OSI Approved :: MIT License
Classifier: Operating System :: OS Independent
License-File: LICENSE
